CapCokor_tiga/__init__.py
CapCokor_tiga/cli.py
CapCokor_tiga-1.1.4.dist-info/METADATA
CapCokor_tiga-1.1.4.dist-info/WHEEL
CapCokor_tiga-1.1.4.dist-info/entry_points.txt
CapCokor_tiga-1.1.4.dist-info/top_level.txt
CapCokor_tiga-1.1.4.dist-info/RECORD
